Metadata-Version: 2.1
Name: lasintaxisxd
Version: 1.5
Summary: Pydefendermalware es un paquete de Python para detectar y eliminar malware en sistemas informáticos. Utiliza técnicas avanzadas de análisis de código malicioso y se integra fácilmente con otros paquetes de seguridad. Con pyantimalware, puedes proteger tu sistema de las últimas amenazas de malware.
Home-page: https://github.com/tuusuario/pyantimalware
Author: $yntaxCode
Author-email: pyantimalware@gmail.com
